ColadaUtility/PowerColor.py
ColadaUtility/PowerLogger.py
ColadaUtility/PowerWinProxy.py
ColadaUtility/__init__.py
ColadaUtility-0.210323.1.dist-info/LICENSE
ColadaUtility-0.210323.1.dist-info/METADATA
ColadaUtility-0.210323.1.dist-info/WHEEL
ColadaUtility-0.210323.1.dist-info/top_level.txt
ColadaUtility-0.210323.1.dist-info/RECORD
